vk_messages/__init__.py
vk_messages/utils.py
vk_messages/vk_messages.py
vk_messages-1.3.dist-info/LICENSE
vk_messages-1.3.dist-info/METADATA
vk_messages-1.3.dist-info/WHEEL
vk_messages-1.3.dist-info/top_level.txt
vk_messages-1.3.dist-info/RECORD
