Metadata-Version: 2.1
Name: vk-messages
Version: 1.3
Summary: Custom library to pass messages API restriction
Home-page: https://github.com/Aragroth/vk_messages/
Author: Aragroth (Osiris)
Author-email: aragroth.osiris@yandex.ru
License: MIT
Download-URL: https://github.com/Aragroth/vk_messages/releases/tag/v1.3
Keywords: API,PYTHON,VK
Platform: UNKNOWN
Classifier: Development Status :: 4 - Beta
Classifier: Intended Audience :: Developers
Classifier: Topic :: Software Development :: Build Tools
Classifier: License :: OSI Approved :: MIT License
Classifier: Programming Language :: Python :: 3.6
Classifier: Programming Language :: Python :: 3.7
License-File: LICENSE
Requires-Dist: requests
Requires-Dist: bs4
